{"skeleton":{"hash":"cZ/NZylh510","spine":"4.1.20","x":-152.89,"y":-201.85,"width":299,"height":462.94,"images":"../images/images/","audio":"C:/Users/hyeon2-400/Desktop/images"},"bones":[{"name":"root"},{"name":"con","parent":"root","x":-0.54,"y":-262.89},{"name":"M_Body","parent":"con","length":294,"rotation":90,"x":0.99,"y":117.28},{"name":"eye_scale","parent":"M_Body","length":280.7,"rotation":90,"x":154.19,"y":-138.65},{"name":"M_Eye_W_4","parent":"eye_scale","rotation":180,"x":52.23,"y":36.85},{"name":"M_Eye_B_4","parent":"M_Eye_W_4","x":1.61,"y":-1.29,"color":"ff3636ff"},{"name":"M_Eye_W_5","parent":"eye_scale","rotation":180,"x":152.66,"y":-13.93},{"name":"M_Eye_B_5","parent":"M_Eye_W_5","x":-1.2,"color":"ff3636ff"},{"name":"M_Eye_W_1","parent":"eye_scale","rotation":180,"x":214.83,"y":-107.19},{"name":"M_Eye_B_1","parent":"M_Eye_W_1","x":-6.38,"y":5.18,"color":"ff3636ff"},{"name":"M_Eye_W_2","parent":"eye_scale","rotation":180,"x":59.4,"y":-106},{"name":"M_Eye_B_2","parent":"M_Eye_W_2","x":-0.4,"y":0.4,"color":"ff3636ff"},{"name":"M_Eye_W_7","parent":"eye_scale","rotation":180,"x":13.16,"y":-37.05},{"name":"M_Eye_W_6","parent":"eye_scale","rotation":180,"x":266.24,"y":-37.05},{"name":"M_Eye_W_3","parent":"eye_scale","rotation":180,"x":249.9,"y":48.64},{"name":"M_Eye_B_3","parent":"M_Eye_W_3","x":-6.38,"y":-1.99,"color":"ff3636ff"},{"name":"M_Leg_3","parent":"con","length":87.68,"rotation":-90,"x":-4.51,"y":149.83},{"name":"M_Leg_2","parent":"con","length":48.43,"rotation":-120.96,"x":-23.37,"y":150.29},{"name":"M_Leg_4","parent":"M_Leg_2","length":47.71,"rotation":-37.9,"x":49.55,"y":-0.71},{"name":"M_Leg_5","parent":"con","length":47.21,"rotation":-59.41,"x":9.56,"y":150.88},{"name":"M_Leg_6","parent":"M_Leg_5","length":50.52,"rotation":36.61,"x":47.72,"y":-0.3},{"name":"M_Leg_1","parent":"con","length":33.87,"rotation":-140.67,"x":-50.31,"y":161.54},{"name":"M_Leg_7","parent":"M_Leg_1","length":27.99,"rotation":-23.49,"x":35.46,"y":-0.36},{"name":"M_Leg_8","parent":"con","length":28.53,"rotation":-37.75,"x":42.11,"y":159.36},{"name":"M_Leg_9","parent":"M_Leg_8","length":27.29,"rotation":21.49,"x":29.61,"y":0.38},{"name":"M_ring_stun","parent":"root","x":2.91,"y":213.33},{"name":"M_Star_stun","parent":"M_ring_stun","x":2.36,"y":20.1},{"name":"M_Star_stun2","parent":"M_ring_stun","x":2.36,"y":20.1}],"slots":[{"name":"M_Eye_W_7","bone":"M_Eye_W_7","attachment":"M_Eye_W_7"},{"name":"M_Eye_W_6","bone":"M_Eye_W_6","attachment":"M_Eye_W_6"},{"name":"M_Leg_5","bone":"M_Leg_9","attachment":"M_Leg_5"},{"name":"M_Leg_4","bone":"M_Leg_6","attachment":"M_Leg_4"},{"name":"M_Leg_3","bone":"M_Leg_3","attachment":"M_Leg_3"},{"name":"M_Leg_2","bone":"M_Leg_4","attachment":"M_Leg_2"},{"name":"M_Leg_1","bone":"M_Leg_7","attachment":"M_Leg_1"},{"name":"M_Body","bone":"M_Body","attachment":"M_Body"},{"name":"M_Eye_W_5","bone":"M_Eye_W_5","attachment":"M_Eye_W_5"},{"name":"M_Eye_B_5","bone":"M_Eye_B_5","attachment":"M_Eye_B_5"},{"name":"M_Eye_W_4","bone":"M_Eye_W_4","attachment":"M_Eye_W_4"},{"name":"M_Eye_B_4","bone":"M_Eye_B_4","attachment":"M_Eye_B_4"},{"name":"M_Eye_W_3","bone":"M_Eye_W_3","attachment":"M_Eye_W_3"},{"name":"M_Eye_B_3","bone":"M_Eye_B_3","attachment":"M_Eye_B_3"},{"name":"M_Eye_W_2","bone":"M_Eye_W_2","attachment":"M_Eye_W_2"},{"name":"M_Eye_B_2","bone":"M_Eye_B_2","attachment":"M_Eye_B_2"},{"name":"M_Eye_W_1","bone":"M_Eye_W_1","attachment":"M_Eye_W_1"},{"name":"M_Eye_B_1","bone":"M_Eye_B_1","attachment":"M_Eye_B_1"},{"name":"M_ring_stun","bone":"M_ring_stun","attachment":"M_ring_stun"},{"name":"M_Star_stun","bone":"M_Star_stun","attachment":"M_Star_stun"},{"name":"M_Star_stun3","bone":"M_Star_stun2","attachment":"M_Star_stun"},{"name":"M_Star_stun2","bone":"M_ring_stun","attachment":"M_Star_stun2"}],"path":[{"name":"M_Star_stun2","bones":["M_Star_stun"],"target":"M_Star_stun2"},{"name":"M_Star_stun3","order":1,"bones":["M_Star_stun2"],"target":"M_Star_stun2"}],"skins":[{"name":"default","attachments":{"M_Body":{"M_Body":{"type":"mesh","uvs":[0.85785,0.08671,0.96589,0.25335,1,0.40628,0.9984,0.61286,0.8958,0.78567,0.78698,0.86529,0.7683,0.93714,0.64403,0.96199,0.50002,0.99999,0.35183,0.96307,0.21021,0.94008,0.19451,0.84731,0.12001,0.79994,0,0.6284,0,0.39439,0.06027,0.23576,0.18413,0.06611,0.40094,0,0.66794,8.0E-4,0.50183,0.83839,0.26189,0.643,0.75366,0.63735,0.51018,0.64008,0.23888,0.40758,0.51698,0.40551,0.77731,0.40621,0.24027,0.26124,0.51267,0.25124,0.77686,0.25851,0.36549,0.13542,0.66462,0.14636,0.51763,0.1078],"triangles":[8,19,7,8,9,19,19,9,11,6,7,5,5,7,19,21,5,19,9,10,11,21,19,22,5,21,4,11,20,19,11,12,20,19,20,22,12,13,20,4,21,3,13,23,20,22,20,24,24,20,23,24,23,26,22,24,21,27,26,29,26,27,24,21,25,3,21,24,25,13,14,23,3,25,2,14,15,23,23,15,26,25,1,2,24,28,25,25,28,1,28,27,30,28,24,27,15,16,26,26,16,29,28,0,1,28,30,0,27,31,30,27,29,31,30,18,0,30,31,18,29,17,31,29,16,17,31,17,18],"vertices":[267.27,-100.58,218.28,-131.8,173.32,-141.66,112.58,-141.19,61.78,-111.54,38.37,-80.09,17.24,-74.69,9.94,-38.78,-1.23,2.84,9.62,45.67,16.38,86.59,43.66,91.13,57.58,112.66,108.02,147.34,176.81,147.34,223.45,129.93,273.33,94.13,292.76,31.47,292.53,-45.69,46.28,2.31,103.72,71.66,105.39,-70.46,104.58,-0.1,172.94,78.31,173.55,-2.06,173.34,-77.3,215.96,77.91,218.9,-0.82,216.76,-77.17,252.95,41.72,249.73,-44.73,261.07,-2.25],"hull":19,"edges":[0,36,4,6,26,28,28,30,34,36,0,2,2,4,30,32,32,34,6,8,24,26,20,22,22,24,8,10,10,12,16,18,18,20,12,14,14,16],"width":289,"height":294}},"M_Eye_B_1":{"M_Eye_B_1":{"x":3.21,"y":-7.3,"width":58,"height":45},"M_Eye_Death_1":{"x":5.39,"y":-7.45,"width":57,"height":51}},"M_Eye_B_2":{"M_Eye_B_2":{"x":-3.2,"y":-2.82,"width":56,"height":50},"M_Eye_Death_2":{"x":2.47,"y":1.03,"width":64,"height":58}},"M_Eye_B_3":{"M_Eye_B_3":{"x":2.78,"y":-0.29,"width":39,"height":79},"M_Eye_Death_3":{"x":0.96,"y":-0.94,"width":48,"height":74}},"M_Eye_B_4":{"M_Eye_B_4":{"x":-2.88,"y":4.21,"width":59,"height":101},"M_Eye_Death_4":{"x":0.79,"y":1.07,"width":71,"height":83}},"M_Eye_B_5":{"M_Eye_B_5":{"x":-4.65,"y":7.14,"width":89,"height":249},"M_Eye_Death_5":{"x":0.03,"y":6.99,"width":89,"height":257}},"M_Eye_W_1":{"M_Eye_W_1":{"x":2.33,"y":-4.62,"width":103,"height":94}},"M_Eye_W_2":{"M_Eye_W_2":{"x":-6.6,"y":-5.42,"width":102,"height":90}},"M_Eye_W_3":{"M_Eye_W_3":{"x":0.9,"y":1.22,"width":78,"height":126}},"M_Eye_W_4":{"M_Eye_W_4":{"x":-4.77,"y":5.42,"width":112,"height":144}},"M_Eye_W_5":{"M_Eye_W_5":{"x":-5.34,"y":2.64,"width":138,"height":278}},"M_Eye_W_6":{"M_Eye_W_6":{"x":-0.26,"y":-3.47,"width":51,"height":66}},"M_Eye_W_7":{"M_Eye_W_7":{"x":-2.83,"y":1.03,"width":46,"height":57}},"M_Leg_1":{"M_Leg_1":{"type":"mesh","uvs":[0.91479,0.01909,1,0.17732,1,0.34238,0.80587,0.63703,0.59346,0.92035,0.24934,0.99712,0.03352,0.88961,0.00839,0.49083,0.21508,0.33541,0.38933,0.29157,0.61656,0.12177,0.74404,0.01909],"triangles":[5,6,7,5,8,9,5,9,4,5,7,8,11,0,1,11,2,10,1,2,11,3,10,2,9,10,3,4,9,3],"vertices":[1,21,-1.87,-5.69,1,1,21,-1.01,3.42,1,1,21,4.01,9.55,1,2,21,21.98,13.11,0.99782,22,-17.72,6.98,0.00218,2,21,40.46,15.55,0.46244,22,-1.75,16.59,0.53756,2,21,58.77,5.31,8.5E-4,22,19.12,14.49,0.99915,1,22,30.17,5.99,1,2,21,54.55,-22.65,0.00193,22,26.39,-12.83,0.99807,2,21,40.22,-20.56,0.13516,22,12.42,-16.62,0.86484,2,21,30.8,-15.56,0.56633,22,1.79,-15.79,0.43367,2,21,15.09,-13.22,0.99379,22,-13.55,-19.91,0.00621,1,21,6.05,-12.18,1],"hull":12,"edges":[0,22,0,2,2,4,8,10,10,12,12,14,14,16,20,22,4,6,6,8,16,18,18,20],"width":60,"height":48}},"M_Leg_2":{"M_Leg_2":{"type":"mesh","uvs":[0.89575,1.0E-5,0.98265,0.04873,0.99806,0.21243,0.93195,0.38747,0.87958,0.49794,0.82103,0.61154,0.73383,0.74347,0.62792,0.8612,0.46701,0.95218,0.25461,0.99999,0.03553,0.93007,1.0E-5,0.81281,0.03857,0.69093,0.32964,0.57034,0.53021,0.40892,0.65915,0.20933,0.78255,0.01851],"triangles":[13,14,6,7,13,6,9,10,11,8,13,7,12,9,11,12,13,9,8,9,13,0,2,16,2,0,1,2,15,16,3,15,2,4,15,3,14,15,4,5,14,4,6,14,5],"vertices":[1,17,-2.54,-3.07,1,1,17,-2.98,4.77,1,1,17,6.91,12.15,1,1,17,20.89,14.37,1,1,17,30.15,15.04,1,1,17,39.87,15.4,1,2,17,51.94,14.51,0.2595,18,-7.47,13.48,0.7405,2,17,63.87,11.79,0.20883,18,3.62,18.66,0.79117,2,17,76.34,4.26,0.0055,18,18.09,20.38,0.9945,1,18,35.23,17.6,1,1,18,49.69,6.39,1,1,18,49.16,-2.84,1,1,18,42.99,-10.26,1,2,17,57.44,-19.9,0.00107,18,18.01,-10.29,0.99893,2,17,38.8,-12.37,0.69503,18,-1.32,-15.8,0.30497,2,17,20.66,-11.22,0.99978,18,-16.34,-26.04,2.2E-4,1,17,3.31,-10.12,1],"hull":17,"edges":[0,32,0,2,2,4,16,18,18,20,20,22,22,24,30,32,28,30,24,26,26,28,4,6,14,16,6,8,8,10,10,12,12,14],"width":80,"height":75}},"M_Leg_3":{"M_Leg_3":{"x":43.79,"y":-1.84,"rotation":90,"width":40,"height":90}},"M_Leg_4":{"M_Leg_4":{"type":"mesh","uvs":[0.19081,0.02734,0.29778,0.19253,0.4754,0.44706,0.7076,0.59665,0.88858,0.6691,0.9645,0.73813,0.97634,0.89115,0.8618,1,0.66984,1,0.45886,0.91628,0.35869,0.84369,0.25446,0.74322,0.20246,0.6798,0.16047,0.62858,0.11291,0.52194,0,0.2406,1.0E-5,0.03854,0.07743,0],"triangles":[12,13,2,11,12,2,10,11,2,10,2,3,9,10,3,8,9,3,8,3,4,4,7,8,6,4,5,6,7,4,16,0,1,0,16,17,14,1,2,1,15,16,14,15,1,13,14,2],"vertices":[1,19,4.82,10.34,1,1,19,19.84,11.4,1,2,19,43.5,13.92,0.63146,20,5.09,13.93,0.36854,2,19,62.62,24.2,0.00196,20,26.56,10.79,0.99804,1,20,42.02,11.39,1,1,20,49.62,8.97,1,1,20,54.94,-1.25,1,1,20,49.66,-12.32,1,1,20,35.5,-18.27,1,1,20,17.51,-19.03,1,1,20,8.01,-17.11,1,1,20,-2.6,-13.4,1,2,19,47.42,-13.76,0.2557,20,-8.27,-10.62,0.7443,2,19,42.4,-14.7,0.46222,20,-12.86,-8.39,0.53778,2,19,33.58,-13.91,0.82985,20,-19.47,-2.49,0.17015,1,19,10.82,-10.94,1,1,19,-2.23,-3.23,1,1,19,-1.56,3.57,1],"hull":18,"edges":[0,34,10,12,12,14,14,16,30,32,32,34,0,2,2,4,4,6,6,8,8,10,16,18,28,30,26,28,18,20,20,22,22,24,24,26],"width":80,"height":75}},"M_Leg_5":{"M_Leg_5":{"type":"mesh","uvs":[0.21271,0,0.53504,0.16214,0.77433,0.28251,0.96553,0.37869,0.96326,0.95174,0.71219,0.95223,0.41732,0.9528,0.19021,0.64721,0.00468,0.39756,0.02603,0],"triangles":[3,5,2,2,6,1,4,5,3,2,5,6,0,8,9,7,0,1,7,8,0,6,7,1],"vertices":[2,23,4.43,9.36,0.99535,24,-20.14,17.58,0.00465,2,23,22.52,14.96,0.47009,24,-1.26,16.16,0.52991,2,23,35.95,19.11,0.00974,24,12.75,15.11,0.99026,1,24,23.95,14.27,1,2,23,60.96,3.78,0,24,30.41,-8.32,1,2,23,50.05,-4.69,0.00692,24,17.16,-12.21,0.99308,2,23,37.25,-14.64,0.32846,24,1.6,-16.77,0.67154,2,23,19.7,-12.38,0.98237,24,-13.9,-8.24,0.01763,1,23,5.36,-10.53,1,1,23,-3.69,3.07,1],"hull":10,"edges":[0,18,6,8,16,18,0,2,12,14,14,16,8,10,10,12,2,4,4,6],"width":55,"height":41}},"M_ring_stun":{"M_ring_stun":{"x":0.77,"y":-1.04,"width":133,"height":43}},"M_Star_stun":{"M_Star_stun":{"x":0.66,"y":-0.47,"width":58,"height":56}},"M_Star_stun2":{"M_Star_stun2":{"type":"path","closed":true,"lengths":[31.82,71.01,105.5,140.42,175.63,210.5,239.24,278.9],"vertexCount":24,"vertices":[13.67,19.23,2.61,19.18,-8.52,19.14,-19.16,18.7,-29.11,17.06,-40.08,15.24,-62.09,8.78,-62.39,-0.47,-62.69,-9.71,-44.17,-15.07,-34.12,-16.86,-23.71,-18.71,-10.11,-19.71,0.66,-19.69,11.42,-19.67,25.59,-19.3,35.74,-17.33,46.1,-15.32,64.89,-10.21,64.52,-1,64.13,8.29,50.9,11.34,41.84,13.83,33.61,16.09]}},"M_Star_stun3":{"M_Star_stun":{"x":0.66,"y":-0.47,"width":58,"height":56}}}}],"animations":{"death":{"slots":{"M_Body":{"rgba":[{"time":0.6,"color":"ffffffff","curve":[0.767,1,0.933,1,0.767,1,0.933,1,0.767,1,0.933,1,0.767,1,0.933,0]},{"time":1.1,"color":"ffffff00"}]},"M_Eye_B_1":{"rgba":[{"time":0.6,"color":"ffffffff","curve":[0.767,1,0.933,1,0.767,1,0.933,1,0.767,1,0.933,1,0.767,1,0.933,0]},{"time":1.1,"color":"ffffff00"}],"attachment":[{"time":0.2667,"name":"M_Eye_Death_1"}]},"M_Eye_B_2":{"rgba":[{"time":0.6,"color":"ffffffff","curve":[0.767,1,0.933,1,0.767,1,0.933,1,0.767,1,0.933,1,0.767,1,0.933,0]},{"time":1.1,"color":"ffffff00"}],"attachment":[{"time":0.2667,"name":"M_Eye_Death_2"}]},"M_Eye_B_3":{"rgba":[{"time":0.6,"color":"ffffffff","curve":[0.767,1,0.933,1,0.767,1,0.933,1,0.767,1,0.933,1,0.767,1,0.933,0]},{"time":1.1,"color":"ffffff00"}],"attachment":[{"time":0.2667,"name":"M_Eye_Death_3"}]},"M_Eye_B_4":{"rgba":[{"time":0.6,"color":"ffffffff","curve":[0.767,1,0.933,1,0.767,1,0.933,1,0.767,1,0.933,1,0.767,1,0.933,0]},{"time":1.1,"color":"ffffff00"}],"attachment":[{"time":0.2667,"name":"M_Eye_Death_4"}]},"M_Eye_B_5":{"rgba":[{"time":0.6,"color":"ffffffff","curve":[0.767,1,0.933,1,0.767,1,0.933,1,0.767,1,0.933,1,0.767,1,0.933,0]},{"time":1.1,"color":"ffffff00"}],"attachment":[{"time":0.2667,"name":"M_Eye_Death_5"}]},"M_Eye_W_1":{"rgba":[{"time":0.6,"color":"ffffffff","curve":[0.767,1,0.933,1,0.767,1,0.933,1,0.767,1,0.933,1,0.767,1,0.933,0]},{"time":1.1,"color":"ffffff00"}]},"M_Eye_W_2":{"rgba":[{"time":0.6,"color":"ffffffff","curve":[0.767,1,0.933,1,0.767,1,0.933,1,0.767,1,0.933,1,0.767,1,0.933,0]},{"time":1.1,"color":"ffffff00"}]},"M_Eye_W_3":{"rgba":[{"time":0.6,"color":"ffffffff","curve":[0.767,1,0.933,1,0.767,1,0.933,1,0.767,1,0.933,1,0.767,1,0.933,0]},{"time":1.1,"color":"ffffff00"}]},"M_Eye_W_4":{"rgba":[{"time":0.6,"color":"ffffffff","curve":[0.767,1,0.933,1,0.767,1,0.933,1,0.767,1,0.933,1,0.767,1,0.933,0]},{"time":1.1,"color":"ffffff00"}]},"M_Eye_W_5":{"rgba":[{"time":0.6,"color":"ffffffff","curve":[0.767,1,0.933,1,0.767,1,0.933,1,0.767,1,0.933,1,0.767,1,0.933,0]},{"time":1.1,"color":"ffffff00"}]},"M_Eye_W_6":{"rgba":[{"time":0.6,"color":"ffffffff","curve":[0.767,1,0.933,1,0.767,1,0.933,1,0.767,1,0.933,1,0.767,1,0.933,0]},{"time":1.1,"color":"ffffff00"}]},"M_Eye_W_7":{"rgba":[{"time":0.6,"color":"ffffffff","curve":[0.767,1,0.933,1,0.767,1,0.933,1,0.767,1,0.933,1,0.767,1,0.933,0]},{"time":1.1,"color":"ffffff00"}]},"M_Leg_1":{"rgba":[{"time":0.6,"color":"ffffffff","curve":[0.767,1,0.933,1,0.767,1,0.933,1,0.767,1,0.933,1,0.767,1,0.933,0]},{"time":1.1,"color":"ffffff00"}]},"M_Leg_2":{"rgba":[{"time":0.6,"color":"ffffffff","curve":[0.767,1,0.933,1,0.767,1,0.933,1,0.767,1,0.933,1,0.767,1,0.933,0]},{"time":1.1,"color":"ffffff00"}]},"M_Leg_3":{"rgba":[{"time":0.6,"color":"ffffffff","curve":[0.767,1,0.933,1,0.767,1,0.933,1,0.767,1,0.933,1,0.767,1,0.933,0]},{"time":1.1,"color":"ffffff00"}]},"M_Leg_4":{"rgba":[{"time":0.6,"color":"ffffffff","curve":[0.767,1,0.933,1,0.767,1,0.933,1,0.767,1,0.933,1,0.767,1,0.933,0]},{"time":1.1,"color":"ffffff00"}]},"M_Leg_5":{"rgba":[{"time":0.6,"color":"ffffffff","curve":[0.767,1,0.933,1,0.767,1,0.933,1,0.767,1,0.933,1,0.767,1,0.933,0]},{"time":1.1,"color":"ffffff00"}]},"M_ring_stun":{"rgba":[{"color":"ffffff00"}]},"M_Star_stun":{"rgba":[{"color":"ffffff00"}]},"M_Star_stun2":{"rgba":[{"color":"ffffff00"}]},"M_Star_stun3":{"rgba":[{"color":"ffffff00"}]}},"bones":{"M_Body":{"scale":[{"curve":[0.089,1,0.178,0.355,0.089,1,0.178,1.769]},{"time":0.2667,"x":0.355,"y":1.769,"curve":[0.344,0.355,0.422,1.465,0.344,1.769,0.422,0.305]},{"time":0.5,"x":1.465,"y":0.305,"curve":[0.633,1.465,0.767,0.904,0.633,0.305,0.767,0.891]},{"time":0.9,"x":0.624,"y":1.185}]},"M_Eye_W_4":{"scale":[{},{"time":0.2333,"x":1.398,"y":0.921},{"time":0.4667}]},"M_Eye_W_5":{"scale":[{},{"time":0.2333,"x":1.398,"y":0.921},{"time":0.4667}]},"M_Eye_W_1":{"scale":[{},{"time":0.2333,"x":1.398,"y":0.921},{"time":0.4667}]},"M_Eye_W_2":{"scale":[{},{"time":0.2333,"x":1.398,"y":0.921},{"time":0.4667}]},"M_Eye_W_7":{"scale":[{},{"time":0.2333,"x":1.897,"y":1.249},{"time":0.4667}]},"M_Eye_W_6":{"scale":[{},{"time":0.2333,"x":1.897,"y":1.249},{"time":0.4667}]},"M_Eye_W_3":{"scale":[{},{"time":0.2333,"x":1.398,"y":0.921},{"time":0.4667}]},"M_Leg_3":{"translate":[{"curve":[0.078,0,0.156,0,0.078,0,0.156,-30.76]},{"time":0.2333,"y":-27.34,"curve":[0.322,0,0.411,0,0.322,-23.42,0.411,14.74]},{"time":0.5,"y":14.74,"curve":[0.633,0,0.767,0,0.633,14.74,0.767,-8.99]},{"time":0.9,"y":-8.99}],"scale":[{},{"time":0.2333,"x":1.164,"y":0.863},{"time":0.5,"x":0.774,"y":1.328},{"time":0.9}]},"M_Leg_2":{"rotate":[{"curve":[0.078,0,0.156,14.8]},{"time":0.2333,"value":14.8,"curve":[0.323,14.8,0.412,-7.15]},{"time":0.5,"value":-10.42,"curve":[0.634,-15.27,0.767,0]},{"time":0.9}],"translate":[{"curve":[0.09,-0.02,0.168,-24.75,0.09,-0.01,0.169,-12.72]},{"time":0.2333,"x":-23.09,"y":-11.56,"curve":[0.407,-18.81,0.499,27.15,0.407,-8.59,0.499,22.66]},{"time":0.5,"x":27.15,"y":22.66,"curve":[0.567,26.99,0.767,5.9,0.589,22.65,0.767,4.1]},{"time":0.9}]},"M_Leg_4":{"rotate":[{},{"time":0.2333,"value":16.79},{"time":0.5,"value":-36.63},{"time":0.9,"value":11.44}]},"M_Leg_5":{"rotate":[{"curve":[0.078,0,0.156,-13.36]},{"time":0.2333,"value":-13.36,"curve":[0.323,-13.36,0.412,13.73]},{"time":0.5,"value":16.68,"curve":[0.612,20.34,0.878,-6.61]},{"time":0.9,"value":-6.61}],"translate":[{"curve":[0.09,0.02,0.169,14.77,0.09,-0.01,0.169,-18.25]},{"time":0.2333,"x":13.32,"y":-16.95,"curve":[0.407,9.61,0.499,-12.82,0.407,-13.6,0.499,11.54]},{"time":0.5,"x":-12.82,"y":11.54,"curve":[0.569,-12.81,0.722,-4.27,0.608,11.34,0.722,3.85]},{"time":0.8333}]},"M_Leg_6":{"rotate":[{},{"time":0.2333,"value":-21.44},{"time":0.5,"value":43.92},{"time":0.9,"value":7.65}]},"M_Leg_1":{"rotate":[{"curve":[0.078,0,0.156,21.92]},{"time":0.2333,"value":21.92,"curve":[0.323,21.92,0.412,-39.06]},{"time":0.5,"value":-43.9,"curve":[0.612,-49.89,0.878,12.15]},{"time":0.9,"value":12.15}],"translate":[{"curve":[0.09,-0.05,0.168,-38.15,0.078,0,0.156,-19.7]},{"time":0.2333,"x":-33.88,"y":-19.7,"curve":[0.406,-22.92,0.498,51.85,0.322,-19.7,0.411,0]},{"time":0.5,"x":51.84,"curve":[0.589,51.5,0.722,18,0.611,0,0.722,0]},{"time":0.8333,"x":5.39}]},"M_Leg_7":{"rotate":[{},{"time":0.2333,"value":18.18},{"time":0.5,"value":-14.93},{"time":0.9,"value":13.54}]},"M_Leg_8":{"rotate":[{"curve":[0.078,0,0.156,-30.94]},{"time":0.2333,"value":-30.94,"curve":[0.323,-30.94,0.412,33.89]},{"time":0.5,"value":40.72,"curve":[0.634,50.87,0.767,-15.02]},{"time":0.9,"value":-15.02}],"translate":[{"curve":[0.09,0.05,0.168,26.43,0.09,0,0.169,-22.32]},{"time":0.2333,"x":22.31,"y":-22.03,"curve":[0.406,11.72,0.498,-36.52,0.407,-21.3,0.5,2.54]},{"time":0.5,"x":-36.53,"y":2.56,"curve":[0.595,-36.79,0.722,-12.18,0.588,11.94,0.722,0.85]},{"time":0.8333}]},"M_Leg_9":{"rotate":[{},{"time":0.2333,"value":-21.19},{"time":0.5,"value":46.38},{"time":0.9,"value":-11.34}]}}},"hit":{"slots":{"M_ring_stun":{"rgba":[{"color":"ffffff00"}]},"M_Star_stun":{"rgba":[{"color":"ffffff00"}]},"M_Star_stun2":{"rgba":[{"color":"ffffff00"}]},"M_Star_stun3":{"rgba":[{"color":"ffffff00"}]}},"bones":{"M_Body":{"scale":[{"curve":[0.04,1,0.21,0.811,0.04,1,0.196,0.95]},{"time":0.2333,"x":0.834,"y":0.95,"curve":[0.248,1.034,0.317,1.3,0.234,0.95,0.317,1.1]},{"time":0.3333,"x":1.3,"y":1.1,"curve":[0.398,1.301,0.426,1.021,0.398,1.1,0.433,1.001]},{"time":0.4333,"curve":[0.449,0.959,0.589,1,0.449,0.962,0.589,1]},{"time":0.6667}]},"M_Eye_W_4":{"scale":[{"curve":[0.222,1,0.157,0.725,0.222,1,0.157,0.725]},{"time":0.2333,"x":0.725,"y":0.725,"curve":[0.267,0.725,0.3,1.224,0.267,0.725,0.3,1.224]},{"time":0.3333,"x":1.246,"y":1.246,"curve":[0.367,1.269,0.4,1.029,0.367,1.269,0.4,1.029]},{"time":0.4333}]},"M_Eye_B_4":{"scale":[{"curve":[0.079,1,0.157,0.725,0.079,1,0.157,0.725]},{"time":0.2333,"x":0.725,"y":0.725,"curve":[0.267,0.725,0.3,1.224,0.267,0.725,0.3,1.224]},{"time":0.3333,"x":1.246,"y":1.246,"curve":[0.367,1.269,0.4,1.029,0.367,1.269,0.4,1.029]},{"time":0.4333,"curve":[0.512,0.931,0.589,1,0.512,0.931,0.589,1]},{"time":0.6667}]},"M_Eye_W_5":{"scale":[{"curve":[0.222,1,0.157,0.725,0.222,1,0.157,0.725]},{"time":0.2333,"x":0.725,"y":0.725,"curve":[0.267,0.725,0.3,1.224,0.267,0.725,0.3,1.224]},{"time":0.3333,"x":1.246,"y":1.246,"curve":[0.367,1.269,0.4,1.029,0.367,1.269,0.4,1.029]},{"time":0.4333}]},"M_Eye_W_1":{"scale":[{"curve":[0.222,1,0.157,0.725,0.222,1,0.157,0.725]},{"time":0.2333,"x":0.725,"y":0.725,"curve":[0.267,0.725,0.3,1.224,0.267,0.725,0.3,1.224]},{"time":0.3333,"x":1.246,"y":1.246,"curve":[0.367,1.269,0.4,1.029,0.367,1.269,0.4,1.029]},{"time":0.4333}]},"M_Eye_B_1":{"scale":[{"curve":[0.222,1,0.157,0.725,0.222,1,0.157,0.725]},{"time":0.2333,"x":0.725,"y":0.725,"curve":[0.267,0.725,0.3,1.224,0.267,0.725,0.3,1.224]},{"time":0.3333,"x":1.246,"y":1.246,"curve":[0.367,1.269,0.4,1.029,0.367,1.269,0.4,1.029]},{"time":0.4333}]},"M_Eye_W_2":{"scale":[{"curve":[0.222,1,0.157,0.725,0.222,1,0.157,0.725]},{"time":0.2333,"x":0.725,"y":0.725,"curve":[0.267,0.725,0.3,1.224,0.267,0.725,0.3,1.224]},{"time":0.3333,"x":1.246,"y":1.246,"curve":[0.367,1.269,0.4,1.029,0.367,1.269,0.4,1.029]},{"time":0.4333}]},"M_Eye_B_2":{"scale":[{"curve":[0.222,1,0.157,0.725,0.222,1,0.157,0.725]},{"time":0.2333,"x":0.725,"y":0.725,"curve":[0.267,0.725,0.3,1.224,0.267,0.725,0.3,1.224]},{"time":0.3333,"x":1.246,"y":1.246,"curve":[0.367,1.269,0.4,1.029,0.367,1.269,0.4,1.029]},{"time":0.4333}]},"M_Eye_W_7":{"scale":[{"curve":[0.222,1,0.157,0.725,0.222,1,0.157,0.725]},{"time":0.2333,"x":0.725,"y":0.725,"curve":[0.267,0.725,0.3,1.224,0.267,0.725,0.3,1.224]},{"time":0.3333,"x":1.246,"y":1.246,"curve":[0.367,1.269,0.4,1.029,0.367,1.269,0.4,1.029]},{"time":0.4333}]},"M_Eye_W_6":{"scale":[{"curve":[0.222,1,0.157,0.725,0.222,1,0.157,0.725]},{"time":0.2333,"x":0.725,"y":0.725,"curve":[0.267,0.725,0.3,1.224,0.267,0.725,0.3,1.224]},{"time":0.3333,"x":1.246,"y":1.246,"curve":[0.367,1.269,0.4,1.029,0.367,1.269,0.4,1.029]},{"time":0.4333}]},"M_Eye_W_3":{"scale":[{"curve":[0.222,1,0.157,0.725,0.222,1,0.157,0.725]},{"time":0.2333,"x":0.725,"y":0.725,"curve":[0.267,0.725,0.3,1.224,0.267,0.725,0.3,1.224]},{"time":0.3333,"x":1.246,"y":1.246,"curve":[0.367,1.269,0.4,1.029,0.367,1.269,0.4,1.029]},{"time":0.4333}]},"M_Eye_B_3":{"scale":[{"curve":[0.222,1,0.157,0.725,0.222,1,0.157,0.725]},{"time":0.2333,"x":0.725,"y":0.725,"curve":[0.267,0.725,0.3,1.224,0.267,0.725,0.3,1.224]},{"time":0.3333,"x":1.246,"y":1.246,"curve":[0.367,1.269,0.4,1.029,0.367,1.269,0.4,1.029]},{"time":0.4333}]},"M_Leg_3":{"scale":[{"curve":[0.102,1,0.134,0.864,0.102,1,0.134,1]},{"time":0.2333,"x":0.864,"curve":[0.267,0.864,0.3,1.681,0.267,1,0.3,1]},{"time":0.3333,"x":1.697,"curve":[0.424,1.739,0.577,1,0.424,1,0.577,1]},{"time":0.6667}]},"M_Leg_2":{"rotate":[{"curve":[0.102,0,0.134,11.87]},{"time":0.2333,"value":11.87,"curve":[0.267,11.87,0.3,-26.17]},{"time":0.3333,"value":-27.52,"curve":[0.419,-31.02,0.581,0]},{"time":0.6667}],"scale":[{"curve":[0.101,1,0.133,0.508,0.101,1,0.133,1]},{"time":0.2333,"x":0.765,"curve":[0.267,0.851,0.3,1.743,0.267,1,0.3,1]},{"time":0.3333,"x":1.743,"curve":[0.42,1.743,0.582,1,0.42,1,0.582,1]},{"time":0.6667}]},"M_Leg_4":{"rotate":[{"curve":[0.098,0,0.138,-38.36]},{"time":0.2333,"value":-38.36,"curve":[0.289,-38.36,0.345,9.72]},{"time":0.4,"value":16.01,"curve":[0.469,23.74,0.599,0]},{"time":0.6667}]},"M_Leg_5":{"rotate":[{"curve":[0.102,0,0.134,-18.37]},{"time":0.2333,"value":-18.37,"curve":[0.267,-18.37,0.3,23.35]},{"time":0.3333,"value":25.45,"curve":[0.419,30.87,0.581,0]},{"time":0.6667}],"scale":[{"curve":[0.101,1,0.133,0.511,0.101,1,0.133,1]},{"time":0.2333,"x":0.743,"curve":[0.267,0.819,0.3,1.667,0.267,1,0.3,1]},{"time":0.3333,"x":1.667,"curve":[0.42,1.667,0.582,1,0.42,1,0.582,1]},{"time":0.6667}]},"M_Leg_6":{"rotate":[{"curve":[0.079,0,0.157,53.68]},{"time":0.2333,"value":53.68,"curve":[0.323,53.68,0.412,17.21]},{"time":0.5,"value":3.12,"curve":[0.556,-5.66,0.611,0]},{"time":0.6667}]},"M_Leg_1":{"rotate":[{"curve":[0.058,0,0.077,20.06]},{"time":0.1333,"value":20.06,"curve":[0.2,20.06,0.267,-53.59]},{"time":0.3333,"value":-58.17,"curve":[0.424,-64.42,0.577,0]},{"time":0.6667}],"scale":[{"curve":[0.058,1,0.076,0.618,0.058,1,0.076,1]},{"time":0.1333,"x":0.765,"curve":[0.2,0.937,0.267,1.743,0.2,1,0.267,1]},{"time":0.3333,"x":1.743,"curve":[0.425,1.743,0.577,1,0.425,1,0.577,1]},{"time":0.6667}]},"M_Leg_8":{"rotate":[{"curve":[0.058,0,0.077,-18.37]},{"time":0.1333,"value":-18.37,"curve":[0.2,-18.37,0.267,54.38]},{"time":0.3333,"value":58.57,"curve":[0.424,64.29,0.577,0]},{"time":0.6667}],"scale":[{"curve":[0.058,1,0.076,0.61,0.058,1,0.076,1]},{"time":0.1333,"x":0.743,"curve":[0.2,0.896,0.267,1.667,0.2,1,0.267,1]},{"time":0.3333,"x":1.667,"curve":[0.425,1.667,0.577,1,0.425,1,0.577,1]},{"time":0.6667}]}},"attachments":{"default":{"M_Body":{"M_Body":{"deform":[{"offset":1,"vertices":[1.30345,0,1.30345,0,1.30345,0,1.30345,0,1.30345,0,1.30345,0,1.30345,0,1.30345,0,1.30345,0,1.30345,0,1.30345,0,1.30345,0,1.30345,0,1.30345,0,1.30345,0,1.30345,0,1.30345,0,1.30345,0,1.30345,0,1.30345,0,-0.86897,0,1.30345,0,1.30345,0,-0.86899,0,1.30345,0,1.30345,0,1.30345,0,1.30345,0,1.30345,0,1.30345,0,1.30345,0,1.30345]}]}}}}},"move":{"slots":{"M_ring_stun":{"rgba":[{"color":"ffffff00"}]},"M_Star_stun":{"rgba":[{"color":"ffffff00"}]},"M_Star_stun2":{"rgba":[{"color":"ffffff00"}]},"M_Star_stun3":{"rgba":[{"color":"ffffff00"}]}},"bones":{"M_Body":{"translate":[{"curve":[0.068,0,0.406,0,0.068,0,0.406,-15.48]},{"time":0.6,"y":-15.48,"curve":[0.781,0,0.922,0,0.781,-15.48,0.922,1.63]},{"time":1.1,"y":6.09,"curve":[1.281,0,1.605,0,1.281,10.55,1.605,0]},{"time":1.6667}],"scale":[{"curve":[0.068,1,0.407,0.858,0.068,1,0.407,1.184]},{"time":0.6,"x":0.858,"y":1.184,"curve":[0.782,0.858,0.923,1.289,0.782,1.184,0.923,0.791]},{"time":1.1,"x":1.387,"y":0.791,"curve":[1.282,1.486,1.605,1,1.282,0.791,1.605,1]},{"time":1.6667}]},"eye_scale":{"translate":[{"curve":[0.068,0,0.402,0,0.068,0,0.402,0]},{"time":0.6}]},"M_Eye_W_4":{"rotate":[{"curve":[0.068,0,0.402,0]},{"time":0.6}],"translate":[{"curve":[0.068,0,0.402,0,0.068,0,0.402,0]},{"time":0.6}]},"M_Eye_B_4":{"scale":[{"curve":[0.068,1,0.405,0.787,0.068,1,0.405,0.787]},{"time":0.6,"x":0.83,"y":0.83,"curve":[0.79,0.872,0.945,1.187,0.79,0.872,0.945,1.187]},{"time":1.1333,"x":1.187,"y":1.187,"curve":[1.306,1.187,1.498,1,1.306,1.187,1.498,1]},{"time":1.6667}]},"M_Eye_W_5":{"rotate":[{"curve":[0.068,0,0.402,0]},{"time":0.6}],"translate":[{"curve":[0.068,0,0.402,0,0.068,0,0.402,0]},{"time":0.6}]},"M_Eye_W_1":{"rotate":[{"curve":[0.068,0,0.402,0]},{"time":0.6}],"translate":[{"curve":[0.068,0,0.402,0,0.068,0,0.402,0]},{"time":0.6}]},"M_Eye_B_1":{"scale":[{"curve":[0.068,1,0.405,0.741,0.068,1,0.405,0.741]},{"time":0.6,"x":0.815,"y":0.815,"curve":[0.782,0.882,0.921,1.318,0.782,0.882,0.921,1.318]},{"time":1.1,"x":1.318,"y":1.318,"curve":[1.281,1.318,1.487,1,1.281,1.318,1.487,1]},{"time":1.6667}]},"M_Eye_W_2":{"rotate":[{"curve":[0.068,0,0.402,0]},{"time":0.6}]},"M_Eye_B_2":{"translate":[{"curve":[0.068,0,0.402,0,0.068,0,0.402,0]},{"time":0.6}],"scale":[{"curve":[0.068,1,0.405,0.711,0.068,1,0.405,0.711]},{"time":0.6,"x":0.759,"y":0.759,"curve":[0.782,0.802,0.921,1.205,0.782,0.802,0.921,1.205]},{"time":1.1,"x":1.205,"y":1.205,"curve":[1.281,1.205,1.487,1,1.281,1.205,1.487,1]},{"time":1.6667}]},"M_Eye_W_7":{"rotate":[{"curve":[0.068,0,0.402,0]},{"time":0.6}],"translate":[{"curve":[0.068,0,0.406,4.08,0.068,0,0.406,-25.38]},{"time":0.6,"x":4.08,"y":-25.38,"curve":[0.781,4.08,0.921,-5.06,0.781,-25.38,0.921,8.3]},{"time":1.1,"x":-6.15,"y":15.07,"curve":[1.281,-7.24,1.487,0,1.281,21.83,1.487,0]},{"time":1.6667}]},"M_Eye_W_6":{"rotate":[{"curve":[0.068,0,0.402,0]},{"time":0.6}],"translate":[{"curve":[0.068,0,0.406,-6.51,0.068,0,0.406,-20.22]},{"time":0.6,"x":-6.51,"y":-20.22,"curve":[0.781,-6.51,0.921,5.34,0.781,-20.22,0.921,15.53]},{"time":1.1,"x":7.07,"y":20.92,"curve":[1.281,8.81,1.487,0,1.281,26.31,1.487,0]},{"time":1.6667}]},"M_Eye_W_3":{"rotate":[{"curve":[0.068,0,0.402,0]},{"time":0.6}]},"M_Eye_B_3":{"scale":[{"curve":[0.068,1,0.406,0.72,0.068,1,0.406,0.72]},{"time":0.6,"x":0.72,"y":0.72,"curve":[0.781,0.72,0.922,1.069,0.781,0.72,0.922,1.069]},{"time":1.1,"x":1.149,"y":1.149,"curve":[1.281,1.23,1.487,1,1.281,1.23,1.487,1]},{"time":1.6667}]},"M_Leg_3":{"rotate":[{"curve":[0.068,0,0.402,0]},{"time":0.6}],"scale":[{"curve":[0.068,1,0.404,0.76,0.068,1,0.404,1]},{"time":0.6,"x":0.76,"curve":[0.78,0.76,0.92,1.474,0.78,1,0.92,1]},{"time":1.1,"x":1.474,"curve":[1.28,1.474,1.487,1,1.28,1,1.487,1]},{"time":1.6667}]},"M_Leg_2":{"rotate":[{"curve":[0.068,0,0.31,-29.05]},{"time":0.6,"value":-29.04,"curve":[0.698,-28.98,0.92,19.63]},{"time":1.1,"value":19.63,"curve":[1.201,19.63,1.302,0.61]},{"time":1.4,"value":-3.82,"curve":[1.48,-7.33,1.587,0]},{"time":1.6667}],"translate":[{"curve":[0.068,0,0.402,0,0.068,0,0.402,3.17]},{"time":0.6,"y":6.07,"curve":[0.767,0,0.933,0,0.767,8.47,0.933,10.7]},{"time":1.1,"y":10.7,"curve":[1.281,0,1.487,0,1.281,10.7,1.487,0]},{"time":1.6667}]},"M_Leg_4":{"rotate":[{"curve":[0.068,0,0.506,141.24]},{"time":0.6,"value":141.24,"curve":[0.78,141.24,0.92,43.72]},{"time":1.1,"value":20.2,"curve":[1.28,-3.33,1.487,0]},{"time":1.6667}],"translate":[{"curve":[0.068,0,0.402,0,0.068,0,0.402,0]},{"time":0.6}]},"M_Leg_5":{"rotate":[{"curve":[0.068,0,0.254,32.11]},{"time":0.6,"value":32.11,"curve":[0.78,32.11,0.92,-18.91]},{"time":1.1,"value":-18.91,"curve":[1.201,-18.91,1.302,2.5]},{"time":1.4,"value":6.77,"curve":[1.48,10.15,1.587,0]},{"time":1.6667}],"translate":[{"curve":[0.068,0,0.402,0,0.068,0,0.402,0]},{"time":0.6}]},"M_Leg_6":{"rotate":[{"curve":[0.068,0,0.506,-144.08]},{"time":0.6,"value":-144.08,"curve":[0.78,-144.08,0.92,-41.54]},{"time":1.1,"value":-18.31,"curve":[1.28,4.92,1.487,0]},{"time":1.6667}]},"M_Leg_1":{"rotate":[{"curve":[0.053,0,0.305,17.07]},{"time":0.6,"value":29.24,"curve":[0.762,35.89,0.937,41.18]},{"time":1.1,"value":41.18,"curve":[1.201,41.18,1.302,-9.63]},{"time":1.4,"value":-18.93,"curve":[1.48,-26.29,1.587,0]},{"time":1.6667}]},"M_Leg_7":{"rotate":[{"curve":[0.068,0,0.506,78.59]},{"time":0.6,"value":78.59,"curve":[0.78,78.59,0.92,-11.58]},{"time":1.1,"value":-11.58,"curve":[1.28,-11.58,1.487,0]},{"time":1.6667}]},"M_Leg_8":{"rotate":[{"curve":[0.068,0,0.249,-24.97]},{"time":0.6,"value":-38.65,"curve":[0.735,-43.71,0.897,-47.55]},{"time":1.1,"value":-47.55,"curve":[1.201,-47.55,1.302,1.61]},{"time":1.4,"value":12.34,"curve":[1.48,20.84,1.587,0]},{"time":1.6667}],"translate":[{"curve":[0.068,0,0.402,0,0.068,0,0.402,0]},{"time":0.6}]},"M_Leg_9":{"rotate":[{"curve":[0.068,0,0.506,-81.12]},{"time":0.6,"value":-81.12,"curve":[0.78,-81.12,0.92,12.62]},{"time":1.1,"value":12.62,"curve":[1.28,12.62,1.487,0]},{"time":1.6667}]}}},"new death":{"slots":{"M_Body":{"rgba":[{"time":0.8333,"color":"ffffffff"},{"time":1.1667,"color":"ffffff00"}]},"M_Eye_B_1":{"rgba":[{"time":0.8333,"color":"ffffffff"},{"time":1.1667,"color":"ffffff00"}],"attachment":[{"name":"M_Eye_Death_1"}]},"M_Eye_B_2":{"rgba":[{"time":0.8333,"color":"ffffffff"},{"time":1.1667,"color":"ffffff00"}],"attachment":[{"name":"M_Eye_Death_2"}]},"M_Eye_B_3":{"rgba":[{"time":0.8333,"color":"ffffffff"},{"time":1.1667,"color":"ffffff00"}],"attachment":[{"name":"M_Eye_Death_3"}]},"M_Eye_B_4":{"rgba":[{"time":0.8333,"color":"ffffffff"},{"time":1.1667,"color":"ffffff00"}],"attachment":[{"name":"M_Eye_Death_4"}]},"M_Eye_B_5":{"rgba":[{"time":0.8333,"color":"ffffffff"},{"time":1.1667,"color":"ffffff00"}],"attachment":[{"name":"M_Eye_Death_5"}]},"M_Eye_W_1":{"rgba":[{"time":0.8333,"color":"ffffffff"},{"time":1.1667,"color":"ffffff00"}]},"M_Eye_W_2":{"rgba":[{"time":0.8333,"color":"ffffffff"},{"time":1.1667,"color":"ffffff00"}]},"M_Eye_W_3":{"rgba":[{"time":0.8333,"color":"ffffffff"},{"time":1.1667,"color":"ffffff00"}]},"M_Eye_W_4":{"rgba":[{"time":0.8333,"color":"ffffffff"},{"time":1.1667,"color":"ffffff00"}]},"M_Eye_W_5":{"rgba":[{"time":0.8333,"color":"ffffffff"},{"time":1.1667,"color":"ffffff00"}]},"M_Eye_W_6":{"rgba":[{"time":0.8333,"color":"ffffffff"},{"time":1.1667,"color":"ffffff00"}]},"M_Eye_W_7":{"rgba":[{"time":0.8333,"color":"ffffffff"},{"time":1.1667,"color":"ffffff00"}]},"M_Leg_1":{"rgba":[{"time":0.8333,"color":"ffffffff"},{"time":1.1667,"color":"ffffff00"}]},"M_Leg_2":{"rgba":[{"time":0.8333,"color":"ffffffff"},{"time":1.1667,"color":"ffffff00"}]},"M_Leg_3":{"rgba":[{"time":0.8333,"color":"ffffffff"},{"time":1.1667,"color":"ffffff00"}]},"M_Leg_4":{"rgba":[{"time":0.8333,"color":"ffffffff"},{"time":1.1667,"color":"ffffff00"}]},"M_Leg_5":{"rgba":[{"time":0.8333,"color":"ffffffff"},{"time":1.1667,"color":"ffffff00"}]},"M_ring_stun":{"rgba":[{"color":"ffffff00"}]},"M_Star_stun":{"rgba":[{"color":"ffffff00"}]},"M_Star_stun2":{"rgba":[{"color":"ffffff00"}]},"M_Star_stun3":{"rgba":[{"color":"ffffff00"}]}},"bones":{"M_Leg_5":{"rotate":[{"value":25.45},{"time":0.2667,"value":-5.94},{"time":0.6333,"value":3.2},{"time":1.3333,"value":22.97}],"scale":[{"x":1.667},{"time":0.2667}]},"con":{"translate":[{"curve":[0.114,0,0.219,0,0.219,-0.13,0.265,145.33]},{"time":0.3333,"y":145.35,"curve":[0.663,0,1.114,0,0.967,145.58,1.333,-133.54]},{"time":1.3333,"y":-150.83}]},"M_Body":{"scale":[{"x":1.043,"y":0.882},{"time":0.1667,"x":1.143,"y":0.852,"curve":"stepped"},{"time":0.3333,"x":1.143,"y":0.852},{"time":1.3333,"x":0.807,"y":1.223}]},"M_Leg_3":{"scale":[{"x":1.697},{"time":0.2667},{"time":1.3333,"x":1.407}]},"M_Leg_2":{"rotate":[{"value":-27.52,"curve":[0.089,-31.16,0.203,8.26]},{"time":0.2667,"value":8.17,"curve":[0.41,7.94,0.458,0.35]},{"time":0.6333,"value":0.32,"curve":[0.646,0.32,1.333,-12.66]},{"time":1.3333,"value":-11.75}],"scale":[{"x":1.743},{"time":0.2667,"x":1.057},{"time":0.6333}]},"M_Leg_1":{"rotate":[{"value":-58.17},{"time":0.2667,"value":20.12},{"time":1.3333,"value":-21.45}],"scale":[{"x":1.743},{"time":0.2667}]},"M_Leg_8":{"rotate":[{"value":58.57},{"time":0.2667,"value":-14.29},{"time":1.3333,"value":13.99}],"scale":[{"x":1.667},{"time":0.2667}]},"M_Leg_6":{"rotate":[{"value":53.68,"curve":[0.046,53.68,0.224,-24.15]},{"time":0.2667,"value":-24.15,"curve":[0.951,-24.15,1.333,8.04]},{"time":1.3333,"value":15.02}]},"M_Leg_4":{"rotate":[{"value":-38.36},{"time":0.2667,"value":13.68},{"time":1.3333,"value":-14.26}]}}},"stun":{"slots":{"M_Eye_B_1":{"attachment":[{"time":0.3333,"name":"M_Eye_Death_1"}]},"M_Eye_B_2":{"attachment":[{"time":0.3333,"name":"M_Eye_Death_2"}]},"M_Eye_B_3":{"attachment":[{"time":0.3333,"name":"M_Eye_Death_3"}]},"M_Eye_B_4":{"attachment":[{"time":0.3333,"name":"M_Eye_Death_4"}]},"M_Eye_B_5":{"attachment":[{"time":0.3333,"name":"M_Eye_Death_5"}]},"M_ring_stun":{"rgba":[{"color":"ffffff00","curve":"stepped"},{"time":0.4,"color":"ffffffff"}]},"M_Star_stun":{"rgba":[{"color":"ffffff00","curve":"stepped"},{"time":0.4,"color":"ffffffff"}]},"M_Star_stun3":{"rgba":[{"color":"ffffff00","curve":"stepped"},{"time":0.4,"color":"ffffffff"}]}},"bones":{"M_Body":{"scale":[{"curve":[0.04,1,0.21,0.811,0.04,1,0.196,0.95]},{"time":0.2333,"x":0.834,"y":0.95,"curve":[0.248,1.034,0.317,1.3,0.234,0.95,0.317,1.1]},{"time":0.3333,"x":1.3,"y":1.1,"curve":[0.356,1.3,0.378,1.043,0.356,1.1,0.378,0.882]},{"time":0.4,"x":1.043,"y":0.882}]},"M_Eye_W_4":{"scale":[{"curve":[0.222,1,0.157,0.725,0.222,1,0.157,0.725]},{"time":0.2333,"x":0.725,"y":0.725,"curve":[0.267,0.725,0.3,1.224,0.267,0.725,0.3,1.224]},{"time":0.3333,"x":1.246,"y":1.246,"curve":[0.346,1.255,0.378,1,0.346,1.255,0.378,1]},{"time":0.4,"curve":[0.422,1,0.434,1.105,0.422,1,0.434,1.105]},{"time":0.4667,"x":1.127,"y":1.127,"curve":[0.489,1.142,0.511,1,0.489,1.142,0.511,1]},{"time":0.5333,"curve":[0.556,1,0.567,1.105,0.556,1,0.567,1.105]},{"time":0.6,"x":1.127,"y":1.127,"curve":[0.622,1.142,0.644,1,0.622,1.142,0.644,1]},{"time":0.6667}]},"M_Eye_B_4":{"scale":[{"curve":[0.079,1,0.157,0.725,0.079,1,0.157,0.725]},{"time":0.2333,"x":0.725,"y":0.725,"curve":[0.267,0.725,0.3,1.224,0.267,0.725,0.3,1.224]},{"time":0.3333,"x":1.246,"y":1.246}]},"M_Eye_W_5":{"scale":[{"curve":[0.222,1,0.157,0.725,0.222,1,0.157,0.725]},{"time":0.2333,"x":0.725,"y":0.725,"curve":[0.267,0.725,0.3,1.224,0.267,0.725,0.3,1.224]},{"time":0.3333,"x":1.246,"y":1.246,"curve":[0.346,1.255,0.378,1,0.346,1.255,0.378,1]},{"time":0.4,"curve":[0.422,1,0.434,1.003,0.422,1,0.434,1.003]},{"time":0.4667,"x":1.025,"y":1.025,"curve":[0.489,1.04,0.511,1,0.489,1.04,0.511,1]},{"time":0.5333,"curve":[0.556,1,0.567,1.003,0.556,1,0.567,1.003]},{"time":0.6,"x":1.025,"y":1.025,"curve":[0.622,1.04,0.644,1,0.622,1.04,0.644,1]},{"time":0.6667}]},"M_Eye_W_1":{"scale":[{"curve":[0.222,1,0.157,0.725,0.222,1,0.157,0.725]},{"time":0.2333,"x":0.725,"y":0.725,"curve":[0.267,0.725,0.3,1.224,0.267,0.725,0.3,1.224]},{"time":0.3333,"x":1.246,"y":1.246,"curve":[0.346,1.255,0.378,1,0.346,1.255,0.378,1]},{"time":0.4,"curve":[0.422,1,0.434,1.105,0.422,1,0.434,1.105]},{"time":0.4667,"x":1.127,"y":1.127,"curve":[0.489,1.142,0.511,1,0.489,1.142,0.511,1]},{"time":0.5333,"curve":[0.556,1,0.567,1.105,0.556,1,0.567,1.105]},{"time":0.6,"x":1.127,"y":1.127,"curve":[0.622,1.142,0.644,1,0.622,1.142,0.644,1]},{"time":0.6667}]},"M_Eye_B_1":{"scale":[{"curve":[0.222,1,0.157,0.725,0.222,1,0.157,0.725]},{"time":0.2333,"x":0.725,"y":0.725,"curve":[0.267,0.725,0.3,1.224,0.267,0.725,0.3,1.224]},{"time":0.3333,"x":1.246,"y":1.246}]},"M_Eye_W_2":{"scale":[{"curve":[0.222,1,0.157,0.725,0.222,1,0.157,0.725]},{"time":0.2333,"x":0.725,"y":0.725,"curve":[0.267,0.725,0.3,1.224,0.267,0.725,0.3,1.224]},{"time":0.3333,"x":1.246,"y":1.246,"curve":[0.346,1.255,0.378,1,0.346,1.255,0.378,1]},{"time":0.4,"curve":[0.422,1,0.434,1.105,0.422,1,0.434,1.105]},{"time":0.4667,"x":1.127,"y":1.127,"curve":[0.489,1.142,0.511,1,0.489,1.142,0.511,1]},{"time":0.5333,"curve":[0.556,1,0.567,1.105,0.556,1,0.567,1.105]},{"time":0.6,"x":1.127,"y":1.127,"curve":[0.622,1.142,0.644,1,0.622,1.142,0.644,1]},{"time":0.6667}]},"M_Eye_B_2":{"scale":[{"curve":[0.222,1,0.157,0.725,0.222,1,0.157,0.725]},{"time":0.2333,"x":0.725,"y":0.725,"curve":[0.267,0.725,0.3,1.224,0.267,0.725,0.3,1.224]},{"time":0.3333,"x":1.246,"y":1.246}]},"M_Eye_W_7":{"scale":[{"curve":[0.222,1,0.157,0.725,0.222,1,0.157,0.725]},{"time":0.2333,"x":0.725,"y":0.725,"curve":[0.267,0.725,0.3,1.224,0.267,0.725,0.3,1.224]},{"time":0.3333,"x":1.246,"y":1.246,"curve":[0.346,1.255,0.378,1,0.346,1.255,0.378,1]},{"time":0.4,"curve":[0.422,1,0.434,1.224,0.422,1,0.434,1.224]},{"time":0.4667,"x":1.246,"y":1.246,"curve":[0.489,1.261,0.511,1,0.489,1.261,0.511,1]},{"time":0.5333,"curve":[0.556,1,0.567,1.224,0.556,1,0.567,1.224]},{"time":0.6,"x":1.246,"y":1.246,"curve":[0.622,1.261,0.644,1,0.622,1.261,0.644,1]},{"time":0.6667}]},"M_Eye_W_6":{"scale":[{"curve":[0.222,1,0.157,0.725,0.222,1,0.157,0.725]},{"time":0.2333,"x":0.725,"y":0.725,"curve":[0.267,0.725,0.3,1.224,0.267,0.725,0.3,1.224]},{"time":0.3333,"x":1.246,"y":1.246,"curve":[0.346,1.255,0.378,1,0.346,1.255,0.378,1]},{"time":0.4,"curve":[0.422,1,0.434,1.224,0.422,1,0.434,1.224]},{"time":0.4667,"x":1.246,"y":1.246,"curve":[0.489,1.261,0.511,1,0.489,1.261,0.511,1]},{"time":0.5333,"curve":[0.556,1,0.567,1.224,0.556,1,0.567,1.224]},{"time":0.6,"x":1.246,"y":1.246,"curve":[0.622,1.261,0.644,1,0.622,1.261,0.644,1]},{"time":0.6667}]},"M_Eye_W_3":{"scale":[{"curve":[0.222,1,0.157,0.725,0.222,1,0.157,0.725]},{"time":0.2333,"x":0.725,"y":0.725,"curve":[0.267,0.725,0.3,1.224,0.267,0.725,0.3,1.224]},{"time":0.3333,"x":1.246,"y":1.246,"curve":[0.346,1.255,0.378,1,0.346,1.255,0.378,1]},{"time":0.4,"curve":[0.422,1,0.434,1.105,0.422,1,0.434,1.105]},{"time":0.4667,"x":1.127,"y":1.127,"curve":[0.489,1.142,0.511,1,0.489,1.142,0.511,1]},{"time":0.5333,"curve":[0.556,1,0.567,1.105,0.556,1,0.567,1.105]},{"time":0.6,"x":1.127,"y":1.127,"curve":[0.622,1.142,0.644,1,0.622,1.142,0.644,1]},{"time":0.6667}]},"M_Eye_B_3":{"scale":[{"curve":[0.222,1,0.157,0.725,0.222,1,0.157,0.725]},{"time":0.2333,"x":0.725,"y":0.725,"curve":[0.267,0.725,0.3,1.224,0.267,0.725,0.3,1.224]},{"time":0.3333,"x":1.246,"y":1.246}]},"M_Leg_3":{"scale":[{"curve":[0.102,1,0.134,0.864,0.102,1,0.134,1]},{"time":0.2333,"x":0.864,"curve":[0.267,0.864,0.3,1.681,0.267,1,0.3,1]},{"time":0.3333,"x":1.697}]},"M_Leg_2":{"rotate":[{"curve":[0.102,0,0.134,11.87]},{"time":0.2333,"value":11.87,"curve":[0.267,11.87,0.3,-26.17]},{"time":0.3333,"value":-27.52}],"scale":[{"curve":[0.101,1,0.133,0.508,0.101,1,0.133,1]},{"time":0.2333,"x":0.765,"curve":[0.267,0.851,0.3,1.743,0.267,1,0.3,1]},{"time":0.3333,"x":1.743}]},"M_Leg_4":{"rotate":[{"curve":[0.098,0,0.138,-38.36]},{"time":0.2333,"value":-38.36}]},"M_Leg_5":{"rotate":[{"curve":[0.102,0,0.134,-18.37]},{"time":0.2333,"value":-18.37,"curve":[0.267,-18.37,0.3,23.35]},{"time":0.3333,"value":25.45}],"scale":[{"curve":[0.101,1,0.133,0.511,0.101,1,0.133,1]},{"time":0.2333,"x":0.743,"curve":[0.267,0.819,0.3,1.667,0.267,1,0.3,1]},{"time":0.3333,"x":1.667}]},"M_Leg_6":{"rotate":[{"curve":[0.079,0,0.157,53.68]},{"time":0.2333,"value":53.68}]},"M_Leg_1":{"rotate":[{"curve":[0.058,0,0.077,20.06]},{"time":0.1333,"value":20.06,"curve":[0.2,20.06,0.267,-53.59]},{"time":0.3333,"value":-58.17}],"scale":[{"curve":[0.058,1,0.076,0.618,0.058,1,0.076,1]},{"time":0.1333,"x":0.765,"curve":[0.2,0.937,0.267,1.743,0.2,1,0.267,1]},{"time":0.3333,"x":1.743}]},"M_Leg_8":{"rotate":[{"curve":[0.058,0,0.077,-18.37]},{"time":0.1333,"value":-18.37,"curve":[0.2,-18.37,0.267,54.38]},{"time":0.3333,"value":58.57}],"scale":[{"curve":[0.058,1,0.076,0.61,0.058,1,0.076,1]},{"time":0.1333,"x":0.743,"curve":[0.2,0.896,0.267,1.667,0.2,1,0.267,1]},{"time":0.3333,"x":1.667}]},"con":{"translate":[{"time":0.3333},{"time":0.4,"x":-8.85},{"time":0.4667,"x":4.41},{"time":0.5333,"x":-8.85},{"time":0.6}]},"M_ring_stun":{"rotate":[{"time":0.4,"value":7.9,"curve":[0.477,4.13,0.564,-6.97]},{"time":0.6667,"value":-6.97,"curve":[0.769,-6.97,0.864,7.9]},{"time":0.9667,"value":7.9,"curve":[1.069,7.9,1.164,-6.97]},{"time":1.2667,"value":-6.97,"curve":[1.369,-6.97,1.493,7.9]},{"time":1.5667,"value":7.9}]},"M_Star_stun":{"rotate":[{"value":-179.78},{"time":0.4,"value":-179.78}]},"M_Star_stun2":{"rotate":[{"value":-179.78},{"time":0.4,"value":-179.78}]}},"path":{"M_Star_stun2":{"position":[{"time":0.4},{"time":1.5667,"value":2}]},"M_Star_stun3":{"position":[{"time":0.4,"value":0.5},{"time":1.5667,"value":2.5}]}},"attachments":{"default":{"M_Body":{"M_Body":{"deform":[{"offset":1,"vertices":[1.30345,0,1.30345,0,1.30345,0,1.30345,0,1.30345,0,1.30345,0,1.30345,0,1.30345,0,1.30345,0,1.30345,0,1.30345,0,1.30345,0,1.30345,0,1.30345,0,1.30345,0,1.30345,0,1.30345,0,1.30345,0,1.30345,0,1.30345,0,-0.86897,0,1.30345,0,1.30345,0,-0.86899,0,1.30345,0,1.30345,0,1.30345,0,1.30345,0,1.30345,0,1.30345,0,1.30345,0,1.30345]}]}}}},"drawOrder":[{"time":0.4,"offsets":[{"slot":"M_ring_stun","offset":1}]},{"time":0.5667,"offsets":[{"slot":"M_Star_stun3","offset":-2}]},{"time":0.8667,"offsets":[{"slot":"M_ring_stun","offset":1}]},{"time":1.1333,"offsets":[{"slot":"M_Star_stun3","offset":-2}]},{"time":1.4333,"offsets":[{"slot":"M_ring_stun","offset":1}]}]}}}