[
	[
		"Index",
		"MaxHP",
		"PCHitboxRad",
		"MovementSpd",
		"ChargeMovementSpd",
		"MercyInvincibleTime",
		"DodgeCooldown",
		"DodgeInvincibleTime",
		"ItemSlotMax",
		"BallStackMax",
		"GoldGain",
		"DefaultBallDataId",
	],
	[
		{
			"Index":"100",
			"MaxHP":"150",
			"PCHitboxRad":"5",
			"MovementSpd":"575",
			"ChargeMovementSpd":"300",
			"MercyInvincibleTime":"3",
			"DodgeCooldown":"2",
			"DodgeInvincibleTime":"0.3",
			"ItemSlotMax":"10",
			"BallStackMax":"1",
			"GoldGain":"1",
			"DefaultBallDataId":"200",
		},
	]
]
