[
	[
		"Index",
		"Name",
		"Desc",
		"PlusDesc",
		"MinusDesc",
		"GradeType",
		"MaxStack",
		"Value",
		"CostHp",
		"CostGold",
		"ItemEffectDataId",
		"ItemIconPath",
	],
	[
		{
			"Index":"10",
			"GradeType":"Hp",
			"MaxStack":"0",
			"Value":"25",
			"CostHp":"0",
			"CostGold":"10",
			"ItemEffectDataId":"0",
		},
		{
			"Index":"11",
			"GradeType":"Hp",
			"MaxStack":"0",
			"Value":"50",
			"CostHp":"0",
			"CostGold":"20",
			"ItemEffectDataId":"0",
		},
		{
			"Index":"20",
			"GradeType":"Gold",
			"MaxStack":"0",
			"Value":"15",
			"CostHp":"25",
			"CostGold":"0",
			"ItemEffectDataId":"0",
			"ItemIconPath":"icon/item/coin.png",
		},
		{
			"Index":"21",
			"GradeType":"Gold",
			"MaxStack":"0",
			"Value":"30",
			"CostHp":"50",
			"CostGold":"0",
			"ItemEffectDataId":"0",
			"ItemIconPath":"icon/item/coin.png",
		},
		{
			"Index":"22",
			"GradeType":"Gold",
			"MaxStack":"0",
			"Value":"45",
			"CostHp":"75",
			"CostGold":"0",
			"ItemEffectDataId":"0",
			"ItemIconPath":"icon/item/coin.png",
		},
		{
			"Index":"2000",
			"Name":"Item_Name_2000",
			"Desc":"Item_Desc_2000",
			"PlusDesc":"Item_PlusDesc_2000",
			"GradeType":"Normal",
			"MaxStack":"0",
			"Value":"1",
			"CostHp":"25",
			"CostGold":"30",
			"ItemEffectDataId":"7000",
			"ItemIconPath":"icon/item/Passive_Item/item_02.png",
		},
		{
			"Index":"2001",
			"Name":"Item_Name_2001",
			"Desc":"Item_Desc_2001",
			"PlusDesc":"Item_PlusDesc_2001",
			"GradeType":"Normal",
			"MaxStack":"0",
			"Value":"1",
			"CostHp":"25",
			"CostGold":"30",
			"ItemEffectDataId":"7001",
			"ItemIconPath":"icon/item/Passive_Item/Item_04_new.png",
		},
		{
			"Index":"2002",
			"Name":"Item_Name_2002",
			"Desc":"Item_Desc_2002",
			"PlusDesc":"Item_PlusDesc_2002",
			"GradeType":"Normal",
			"MaxStack":"0",
			"Value":"1",
			"CostHp":"25",
			"CostGold":"30",
			"ItemEffectDataId":"7002",
			"ItemIconPath":"icon/item/Passive_Item/item_05.png",
		},
		{
			"Index":"2003",
			"Name":"Item_Name_2003",
			"Desc":"Item_Desc_2003",
			"PlusDesc":"Item_PlusDesc_2003",
			"GradeType":"Normal",
			"MaxStack":"0",
			"Value":"1",
			"CostHp":"25",
			"CostGold":"30",
			"ItemEffectDataId":"7003",
			"ItemIconPath":"icon/item/Passive_Item/item_07.png",
		},
		{
			"Index":"2004",
			"Name":"Item_Name_2004",
			"Desc":"Item_Desc_2004",
			"PlusDesc":"Item_PlusDesc_2004",
			"GradeType":"Normal",
			"MaxStack":"0",
			"Value":"1",
			"CostHp":"25",
			"CostGold":"30",
			"ItemEffectDataId":"7004",
			"ItemIconPath":"icon/item/Passive_Item/item_11.png",
		},
		{
			"Index":"2005",
			"Name":"Item_Name_2005",
			"Desc":"Item_Desc_2005",
			"PlusDesc":"Item_PlusDesc_2005",
			"GradeType":"Normal",
			"MaxStack":"0",
			"Value":"1",
			"CostHp":"25",
			"CostGold":"30",
			"ItemEffectDataId":"7005",
			"ItemIconPath":"icon/item/Passive_Item/item_15.png",
		},
		{
			"Index":"3000",
			"Name":"Item_Name_3000",
			"Desc":"Item_Desc_3000",
			"PlusDesc":"Item_PlusDesc_3000",
			"GradeType":"Rare",
			"MaxStack":"0",
			"Value":"1",
			"CostHp":"50",
			"CostGold":"50",
			"ItemEffectDataId":"8000",
			"ItemIconPath":"icon/item/Passive_Item/item_17.png",
		},
		{
			"Index":"3001",
			"Name":"Item_Name_3001",
			"Desc":"Item_Desc_3001",
			"PlusDesc":"Item_PlusDesc_3001",
			"GradeType":"Rare",
			"MaxStack":"0",
			"Value":"1",
			"CostHp":"50",
			"CostGold":"50",
			"ItemEffectDataId":"8001",
			"ItemIconPath":"icon/item/Passive_Item/item_12_new.png",
		},
		{
			"Index":"3002",
			"Name":"Item_Name_3002",
			"Desc":"Item_Desc_3002",
			"PlusDesc":"Item_PlusDesc_3002",
			"GradeType":"Rare",
			"MaxStack":"0",
			"Value":"1",
			"CostHp":"50",
			"CostGold":"50",
			"ItemEffectDataId":"8002",
			"ItemIconPath":"icon/item/Passive_Item/item_09.png",
		},
		{
			"Index":"3003",
			"Name":"Item_Name_3003",
			"Desc":"Item_Desc_3003",
			"PlusDesc":"Item_PlusDesc_3003",
			"GradeType":"Rare",
			"MaxStack":"0",
			"Value":"1",
			"CostHp":"50",
			"CostGold":"50",
			"ItemEffectDataId":"8003",
			"ItemIconPath":"icon/item/Passive_Item/item_10.png",
		},
		{
			"Index":"3004",
			"Name":"Item_Name_3004",
			"Desc":"Item_Desc_3004",
			"PlusDesc":"Item_PlusDesc_3004",
			"GradeType":"Rare",
			"MaxStack":"0",
			"Value":"1",
			"CostHp":"50",
			"CostGold":"50",
			"ItemEffectDataId":"8004",
			"ItemIconPath":"icon/item/Passive_Item/item_16.png",
		},
		{
			"Index":"3005",
			"Name":"Item_Name_3005",
			"Desc":"Item_Desc_3005",
			"PlusDesc":"Item_PlusDesc_3005",
			"GradeType":"Rare",
			"MaxStack":"0",
			"Value":"1",
			"CostHp":"50",
			"CostGold":"50",
			"ItemEffectDataId":"8005",
			"ItemIconPath":"icon/item/Passive_Item/item_03.png",
		},
		{
			"Index":"3006",
			"Name":"Item_Name_3006",
			"Desc":"Item_Desc_3006",
			"PlusDesc":"Item_PlusDesc_3006",
			"GradeType":"Rare",
			"MaxStack":"0",
			"Value":"1",
			"CostHp":"50",
			"CostGold":"50",
			"ItemEffectDataId":"8006",
			"ItemIconPath":"icon/item/Passive_Item/item_18.png",
		},
		{
			"Index":"3007",
			"Name":"Item_Name_3007",
			"Desc":"Item_Desc_3007",
			"PlusDesc":"Item_PlusDesc_3007",
			"GradeType":"Rare",
			"MaxStack":"6",
			"Value":"1",
			"CostHp":"50",
			"CostGold":"50",
			"ItemEffectDataId":"8007",
			"ItemIconPath":"icon/item/Passive_Item/item_01.png",
		},
		{
			"Index":"4000",
			"Name":"Item_Name_4000",
			"Desc":"Item_Desc_4000",
			"PlusDesc":"Item_PlusDesc_4000",
			"MinusDesc":"Item_MinusDesc_4000",
			"GradeType":"Cursed",
			"MaxStack":"0",
			"Value":"1",
			"CostHp":"50",
			"CostGold":"60",
			"ItemEffectDataId":"9000",
			"ItemIconPath":"icon/item/Passive_Item/item_06.png",
		},
		{
			"Index":"4001",
			"Name":"Item_Name_4001",
			"Desc":"Item_Desc_4001",
			"PlusDesc":"Item_PlusDesc_4001",
			"MinusDesc":"Item_MinusDesc_4001",
			"GradeType":"Cursed",
			"MaxStack":"0",
			"Value":"1",
			"CostHp":"50",
			"CostGold":"60",
			"ItemEffectDataId":"9001",
			"ItemIconPath":"icon/item/Passive_Item/item_08.png",
		},
		{
			"Index":"4002",
			"Name":"Item_Name_4002",
			"Desc":"Item_Desc_4002",
			"PlusDesc":"Item_PlusDesc_4002",
			"MinusDesc":"Item_MinusDesc_4002",
			"GradeType":"Cursed",
			"MaxStack":"0",
			"Value":"1",
			"CostHp":"50",
			"CostGold":"60",
			"ItemEffectDataId":"9002",
			"ItemIconPath":"icon/item/Passive_Item/item_14_new.png",
		},
		{
			"Index":"4003",
			"Name":"Item_Name_4003",
			"Desc":"Item_Desc_4003",
			"PlusDesc":"Item_PlusDesc_4003",
			"MinusDesc":"Item_MinusDesc_4003",
			"GradeType":"Cursed",
			"MaxStack":"0",
			"Value":"1",
			"CostHp":"50",
			"CostGold":"60",
			"ItemEffectDataId":"9003",
			"ItemIconPath":"icon/item/Passive_Item/item_01.png",
		},
		{
			"Index":"4004",
			"Name":"Item_Name_4004",
			"Desc":"Item_Desc_4004",
			"PlusDesc":"Item_PlusDesc_4004",
			"MinusDesc":"Item_MinusDesc_4004",
			"GradeType":"Cursed",
			"MaxStack":"0",
			"Value":"1",
			"CostHp":"50",
			"CostGold":"60",
			"ItemEffectDataId":"9004",
			"ItemIconPath":"icon/item/Passive_Item/item_13.png",
		},
		{
			"Index":"4005",
			"Name":"Item_Name_4005",
			"Desc":"Item_Desc_4005",
			"PlusDesc":"Item_PlusDesc_4005",
			"MinusDesc":"Item_MinusDesc_4005",
			"GradeType":"Cursed",
			"MaxStack":"0",
			"Value":"1",
			"CostHp":"50",
			"CostGold":"60",
			"ItemEffectDataId":"9005",
			"ItemIconPath":"icon/item/Passive_Item/item_20_new.png",
		},
		{
			"Index":"4006",
			"Name":"Item_Name_4006",
			"Desc":"Item_Desc_4006",
			"PlusDesc":"Item_PlusDesc_4006",
			"MinusDesc":"Item_MinusDesc_4006",
			"GradeType":"Cursed",
			"MaxStack":"0",
			"Value":"1",
			"CostHp":"50",
			"CostGold":"60",
			"ItemEffectDataId":"9006",
			"ItemIconPath":"icon/item/Passive_Item/item_19_new.png",
		},
		{
			"Index":"10000",
			"Name":"Item_Name_10000",
			"Desc":"Item_Desc_10000",
			"PlusDesc":"Item_PlusDesc_10000",
			"GradeType":"Active",
			"MaxStack":"0",
			"Value":"1",
			"CostHp":"50",
			"CostGold":"100",
			"ItemEffectDataId":"10000",
			"ItemIconPath":"icon/item/Active_item/A_item_02.png",
		},
		{
			"Index":"10001",
			"Name":"Item_Name_10001",
			"Desc":"Item_Desc_10001",
			"PlusDesc":"Item_PlusDesc_10001",
			"GradeType":"Active",
			"MaxStack":"0",
			"Value":"1",
			"CostHp":"50",
			"CostGold":"100",
			"ItemEffectDataId":"10001",
			"ItemIconPath":"icon/item/Active_item/A_item_03.png",
		},
		{
			"Index":"10002",
			"Name":"Item_Name_10002",
			"Desc":"Item_Desc_10002",
			"PlusDesc":"Item_PlusDesc_10002",
			"GradeType":"Active",
			"MaxStack":"0",
			"Value":"1",
			"CostHp":"50",
			"CostGold":"100",
			"ItemEffectDataId":"10002",
			"ItemIconPath":"icon/item/Active_item/A_item_06.png",
		},
		{
			"Index":"10003",
			"Name":"Item_Name_10003",
			"Desc":"Item_Desc_10003",
			"PlusDesc":"Item_PlusDesc_10003",
			"GradeType":"Active",
			"MaxStack":"3",
			"Value":"1",
			"CostHp":"50",
			"CostGold":"100",
			"ItemEffectDataId":"10003",
			"ItemIconPath":"icon/item/Active_item/A_item_01.png",
		},
		{
			"Index":"10005",
			"Name":"Item_Name_10005",
			"Desc":"Item_Desc_10005",
			"PlusDesc":"Item_PlusDesc_10005",
			"GradeType":"Active",
			"MaxStack":"0",
			"Value":"1",
			"CostHp":"50",
			"CostGold":"100",
			"ItemEffectDataId":"10005",
			"ItemIconPath":"icon/item/Active_item/A_item_07.png",
		},
	]
]
